odoo_ninja/__init__.py
odoo_ninja/auth.py
odoo_ninja/base.py
odoo_ninja/client.py
odoo_ninja/config.py
odoo_ninja/helpdesk.py
odoo_ninja/main.py
odoo_ninja/project.py
odoo_ninja/project_project.py
odoo_ninja-0.3.0.dist-info/METADATA
odoo_ninja-0.3.0.dist-info/WHEEL
odoo_ninja-0.3.0.dist-info/entry_points.txt
odoo_ninja-0.3.0.dist-info/licenses/LICENSE
odoo_ninja-0.3.0.dist-info/RECORD
