Metadata-Version: 2.4
Name: odoo-ninja
Version: 0.3.0
Summary: Modern Python CLI for Odoo with support for helpdesk, projects, and tasks
Project-URL: Homepage, https://github.com/semadox/odoo-ninja
Project-URL: Repository, https://github.com/semadox/odoo-ninja
Project-URL: Issues, https://github.com/semadox/odoo-ninja/issues
Author-email: Julian Rath <julian.rath@semadox.com>
Maintainer-email: Semadox GmbH <info@semadox.com>
License: MIT
License-File: LICENSE
Keywords: cli,helpdesk,management,odoo,project,task,xmlrpc
Classifier: Development Status :: 4 - Beta
Classifier: Intended Audience :: Developers
Classifier: Intended Audience :: System Administrators
Classifier: License :: OSI Approved :: MIT License
Classifier: Programming Language :: Python :: 3
Classifier: Programming Language :: Python :: 3.12
Classifier: Topic :: Office/Business
Classifier: Topic :: Software Development :: Libraries :: Python Modules
Classifier: Topic :: Utilities
Classifier: Typing :: Typed
Requires-Python: >=3.12
Requires-Dist: markdown>=3.5.0
Requires-Dist: pydantic-settings>=2.5.0
Requires-Dist: pydantic>=2.9.0
Requires-Dist: python-dotenv>=1.0.0
Requires-Dist: rich>=13.7.0
Requires-Dist: typer[all]>=0.12.0
Provides-Extra: dev
Requires-Dist: mypy>=1.11.0; extra == 'dev'
Requires-Dist: ruff>=0.6.0; extra == 'dev'
Requires-Dist: types-markdown>=3.5.0; extra == 'dev'
